src/hola/__init__.py
src/hola/example.py
herram-1.0.0.dist-info/METADATA
herram-1.0.0.dist-info/WHEEL
herram-1.0.0.dist-info/RECORD
