Metadata-Version: 2.1
Name: herram
Version: 1.0.0
Summary: A small example package
Project-URL: Homepage, https://github.com/DIEGOMR18059/ProyectoH-final
Project-URL: Issues, https://github.com/DIEGOMR18059/ProyectoH-final/issues
Author-email: Diego Mares Rodriguez <diegomares795283@gmail.com>
Classifier: License :: OSI Approved :: MIT License
Classifier: Operating System :: OS Independent
Classifier: Programming Language :: Python :: 3
Requires-Python: >=3.7
Requires-Dist: matplotlib==3.8.1
Requires-Dist: numpy==1.26.0
Requires-Dist: scipy==1.11.3
